<?xml version="1.0" encoding="utf-8"?>
<Version>
  <CurrentVersion Number="5" Version="2.0.2.5" String="2.0.2.5" />

  <Changelog>
    <Release Version="2.0.2.5">
      <Change>Added 'includeFiles' field for ModInfo.json files: whether to include files in .tapi archive or not.</Change>
    </Release>
    <Release Version="2.0.2.4">
      <Change>Fixed a bug when non-CompilerWarning warnings are reported as errors.</Change>
      <Change>The .svn and .vs directories are now ignored, too.</Change>
    </Release>
    <Release Version="2.0.2.3">
      <Change>Removed the file porter (An official one will be added in r15).</Change>
      <Change>PDB files are now written to a different directory (r14a).</Change>
    </Release>
    <Release Version="2.0.2.2">
      <Change>Updated to r14a.</Change>
    </Release>
    <Release Version="2.0.2.1">
      <Change>Fixed some bugs in the MCT compiler.</Change>
    </Release>
    <Release Version="2.0.2.0">
      <Change>Added TextBox.DefaultText.</Change>
    </Release>
    <Release Version="2.0.1.0">
      <Change>Fixed a bug that caused the MCT sometimes not being loaded at all (I hope).</Change>
      <Change>PoroCYon.MCT is now an APIModBase.</Change>
    </Release>
    <Release Version="2.0.0.5">
      <Change>Updated to r12.</Change>
    </Release>
    <Release Version="2.0.0.4">
      <Change>Enhanced the type checker of the mod compiler a bit.</Change>
    </Release>
    <Release Version="2.0.0.3">
      <Change>Fixed even more bugs, related to dedicated server stuff.</Change>
    </Release>
    <Release Version="2.0.0.2">
      <Change>Fixed more hidden bugs.</Change>
    </Release>
    <Release Version="2.0.0.1">
      <Change>Fixed some bugs that came with the r11 release.</Change>
    </Release>
    <Release Version="2.0.0.0">
      <Change>Updated to r11.</Change>
    </Release>
  </Changelog>
</Version>
